LICENSE
MANIFEST.in
README.md
package_desc.md
pyproject.toml
setup.py
setup.requirements.txt
taipy/__init__.py
taipy/common/__init__.py
taipy/common/setup.py
taipy/common/version.json
taipy/common/version.py
taipy/common/_cli/__init__.py
taipy/common/_cli/_create_cli.py
taipy/common/_cli/_help_cli.py
taipy/common/_cli/_run_cli.py
taipy/common/_cli/_base_cli/__init__.py
taipy/common/_cli/_base_cli/_abstract_cli.py
taipy/common/_cli/_base_cli/_taipy_parser.py
taipy/common/config/__init__.py
taipy/common/config/_config.py
taipy/common/config/_init.py
taipy/common/config/config.py
taipy/common/config/config.pyi
taipy/common/config/section.py
taipy/common/config/unique_section.py
taipy/common/config/_config_comparator/__init__.py
taipy/common/config/_config_comparator/_comparator_result.py
taipy/common/config/_config_comparator/_config_comparator.py
taipy/common/config/_serializer/__init__.py
taipy/common/config/_serializer/_base_serializer.py
taipy/common/config/_serializer/_json_serializer.py
taipy/common/config/_serializer/_toml_serializer.py
taipy/common/config/checker/__init__.py
taipy/common/config/checker/_checker.py
taipy/common/config/checker/issue.py
taipy/common/config/checker/issue_collector.py
taipy/common/config/checker/_checkers/__init__.py
taipy/common/config/checker/_checkers/_auth_config_checker.py
taipy/common/config/checker/_checkers/_config_checker.py
taipy/common/config/common/__init__.py
taipy/common/config/common/_classproperty.py
taipy/common/config/common/_config_blocker.py
taipy/common/config/common/_repr_enum.py
taipy/common/config/common/_template_handler.py
taipy/common/config/common/_validate_id.py
taipy/common/config/common/frequency.py
taipy/common/config/common/scope.py
taipy/common/config/common/typing.py
taipy/common/config/exceptions/__init__.py
taipy/common/config/exceptions/exceptions.py
taipy/common/config/global_app/__init__.py
taipy/common/config/global_app/global_app_config.py
taipy/common/config/stubs/generate_pyi.py
taipy_common.egg-info/PKG-INFO
taipy_common.egg-info/SOURCES.txt
taipy_common.egg-info/dependency_links.txt
taipy_common.egg-info/requires.txt
taipy_common.egg-info/top_level.txt