Metadata-Version: 2.4
Name: taipy-common
Version: 4.1.0
Summary: A Taipy package dedicated to provide common data structures, types, classes and functions.
Author-email: Avaiga <dev@taipy.io>
License-Expression: Apache-2.0
Project-URL: Homepage, https://github.com/Avaiga/taipy
Keywords: taipy,taipy-common
Classifier: Intended Audience :: Developers
Classifier: Natural Language :: English
Classifier: Programming Language :: Python :: 3
Classifier: Programming Language :: Python :: 3.9
Classifier: Programming Language :: Python :: 3.10
Classifier: Programming Language :: Python :: 3.11
Classifier: Programming Language :: Python :: 3.12
Requires-Python: <3.13,>=3.9
License-File: LICENSE
Requires-Dist: deepdiff<=7.0.1,>=6.7.0
Requires-Dist: toml<=0.10.2,>=0.10
Provides-Extra: test
Requires-Dist: pytest>=6.0; extra == "test"
Dynamic: license-file
Dynamic: requires-dist
